testpackage/__init__.py
testpackage/module.py
dgjiberg-0.1.4.dist-info/LICENSE
dgjiberg-0.1.4.dist-info/METADATA
dgjiberg-0.1.4.dist-info/WHEEL
dgjiberg-0.1.4.dist-info/top_level.txt
dgjiberg-0.1.4.dist-info/RECORD
