Metadata-Version: 2.1
Name: dgjiberg
Version: 0.1.4
Summary: Description
Home-page: UNKNOWN
Author: JosquinHa
License: UNKNOWN
Platform: UNKNOWN
Classifier: Programming Language :: Python :: 3
Classifier: License :: OSI Approved :: MIT License
Classifier: Operating System :: OS Independent
